countdown_tray-1.1.1.dist-info/METADATA
countdown_tray-1.1.1.dist-info/WHEEL
countdown_tray-1.1.1.dist-info/entry_points.txt
countdown_tray.py
countdown_tray-1.1.1.dist-info/RECORD
