Metadata-Version: 2.1
Name: countdown-tray
Version: 1.1.1
Summary: Create a system tray icon that counts down
Author-Email: Ethan Dawes <ethand.python@gmail.com>
License: MIT
Classifier: Programming Language :: Python :: 3
Classifier: License :: OSI Approved :: MIT License
Classifier: Operating System :: OS Independent
Project-URL: Homepage, https://github.com/funblaster22/countdown-tray
Project-URL: Issues, https://github.com/funblaster22/countdown-tray/issues
Requires-Python: >=3.9
Requires-Dist: pystray>=0.19.5
Requires-Dist: pillow>=11.0.0
Requires-Dist: cronsim>=2.6
